{
  "request_id": "9c1a98f7-e7cf-4b4c-8ccb-7df9754d6fc4",
  "trace_id": "9fed0bc8-23a1-4317-99c8-3c34c72e41ac",
  "detail": {},
  "code": "0",
  "message": "SUCCESS",
  "svc_code": 0,
  "sdk_res_code": 0,
  "data": {
    "accounts": [
      {
        "id": "9",
        "guid": "MOCK_GUID1",
        "platform": "MOCK_PLATFORM",
        "npa_code": "0K800KI100001",
        "game_name": "MOCK_GAME_NAME",
        "service_id": "MOCK_SERVICE_ID",
        "platform_login_id": "",
        "enable": 1,
        "intended_use": "Test usage confirmation",
        "memo": "",
        "created_at": "2025-10-03T06:16:32.811Z",
        "updated_at": "2025-10-15T06:30:00.000Z",
        "reminder_start_at": "2025-10-15T06:30:00.384Z",
        "confirm_deadline": "2025-11-14T06:30:00.000Z",
        "registrant_name": "Nguyen Tri Duc",
        "registrant_email": "untitleduck@nexondv.com",
        "registrant_emp_no": "D3981",
        "registrant_department": "WebDev Team 1",
        "registrant_company_code": "VL",
        "manager_name": "Vo Minh Tuan",
        "manager_email": "Baron@nexondv.com",
        "manager_emp_no": "D4233",
        "manager_department": "WebDev Team 1",
        "manager_company_code": "VL",
        "employee_name": "Tran Luong Danh",
        "employee_email": "danh2k@nexondv.com",
        "employee_emp_no": "C9104",
        "employee_department": "WebDev Team 1",
        "employee_company_code": "VL"
      },
      {
        "id": "11",
        "guid": "MOCK_GUID3",
        "platform": "MOCK_PLATFORM",
        "npa_code": "0K800KI100003",
        "game_name": "MOCK_GAME_NAME",
        "service_id": "MOCK_SERVICE_ID",
        "platform_login_id": "abcd",
        "enable": 1,
        "intended_use": "Test usage confirmation",
        "memo": "string1",
        "created_at": "2025-10-03T06:16:45.989Z",
        "updated_at": "2025-10-15T06:20:00.000Z",
        "reminder_start_at": "2025-10-15T06:20:00.183Z",
        "confirm_deadline": "2025-11-14T06:20:00.000Z",
        "registrant_name": "Nguyen Tri Duc",
        "registrant_email": "untitleduck@nexondv.com",
        "registrant_emp_no": "D3981",
        "registrant_department": "WebDev Team 1",
        "registrant_company_code": "VL",
        "manager_name": "Vo Minh Tuan",
        "manager_email": "Baron@nexondv.com",
        "manager_emp_no": "D4233",
        "manager_department": "WebDev Team 1",
        "manager_company_code": "VL",
        "employee_name": "Tran Luong Danh",
        "employee_email": "danh2k@nexondv.com",
        "employee_emp_no": "C9104",
        "employee_department": "WebDev Team 1",
        "employee_company_code": "VL"
      },
      {
        "id": "12",
        "guid": "MOCK_GUID4",
        "platform": "MOCK_PLATFORM",
        "npa_code": "0K800KI100004",
        "game_name": "MOCK_GAME_NAME",
        "service_id": "MOCK_SERVICE_ID",
        "platform_login_id": "",
        "enable": 1,
        "intended_use": "Test usage confirmation",
        "memo": "Test usage confirmation",
        "created_at": "2025-10-03T06:16:51.023Z",
        "updated_at": "2025-10-15T06:30:00.000Z",
        "reminder_start_at": "2025-10-15T06:30:00.384Z",
        "confirm_deadline": "2025-11-14T06:30:00.000Z",
        "registrant_name": "Nguyen Tri Duc",
        "registrant_email": "untitleduck@nexondv.com",
        "registrant_emp_no": "D3981",
        "registrant_department": "WebDev Team 1",
        "registrant_company_code": "VL",
        "manager_name": "Vo Minh Tuan",
        "manager_email": "Baron@nexondv.com",
        "manager_emp_no": "D4233",
        "manager_department": "WebDev Team 1",
        "manager_company_code": "VL",
        "employee_name": "Tran Luong Danh",
        "employee_email": "danh2k@nexondv.com",
        "employee_emp_no": "C9104",
        "employee_department": "WebDev Team 1",
        "employee_company_code": "VL"
      },
      {
        "id": "13",
        "guid": "MOCK_GUID5",
        "platform": "MOCK_PLATFORM",
        "npa_code": "0K800KI100005",
        "game_name": "MOCK_GAME_NAME",
        "service_id": "MOCK_SERVICE_ID",
        "platform_login_id": "",
        "enable": 1,
        "intended_use": "Test usage confirmation",
        "memo": "Test usage confirmation",
        "created_at": "2025-10-03T06:16:57.769Z",
        "updated_at": "2025-10-15T06:20:00.000Z",
        "reminder_start_at": "2025-10-15T06:20:00.183Z",
        "confirm_deadline": "2025-11-14T06:20:00.000Z",
        "registrant_name": "Nguyen Tri Duc",
        "registrant_email": "untitleduck@nexondv.com",
        "registrant_emp_no": "D3981",
        "registrant_department": "WebDev Team 1",
        "registrant_company_code": "VL",
        "manager_name": "Vo Minh Tuan",
        "manager_email": "Baron@nexondv.com",
        "manager_emp_no": "D4233",
        "manager_department": "WebDev Team 1",
        "manager_company_code": "VL",
        "employee_name": "Tran Luong Danh",
        "employee_email": "danh2k@nexondv.com",
        "employee_emp_no": "C9104",
        "employee_department": "WebDev Team 1",
        "employee_company_code": "VL"
      },
      {
        "id": "14",
        "guid": "MOCK_GUID6",
        "platform": "MOCK_PLATFORM",
        "npa_code": "0K800KI100006",
        "game_name": "MOCK_GAME_NAME",
        "service_id": "MOCK_SERVICE_ID",
        "platform_login_id": "",
        "enable": 1,
        "intended_use": "Test usage confirmation",
        "memo": "Test usage confirmation",
        "created_at": "2025-10-03T06:17:03.253Z",
        "updated_at": "2025-10-15T06:30:00.000Z",
        "reminder_start_at": "2025-10-15T06:30:00.384Z",
        "confirm_deadline": "2025-11-14T06:30:00.000Z",
        "registrant_name": "Nguyen Tri Duc",
        "registrant_email": "untitleduck@nexondv.com",
        "registrant_emp_no": "D3981",
        "registrant_department": "WebDev Team 1",
        "registrant_company_code": "VL",
        "manager_name": "Vo Minh Tuan",
        "manager_email": "Baron@nexondv.com",
        "manager_emp_no": "D4233",
        "manager_department": "WebDev Team 1",
        "manager_company_code": "VL",
        "employee_name": "Tran Luong Danh",
        "employee_email": "danh2k@nexondv.com",
        "employee_emp_no": "C9104",
        "employee_department": "WebDev Team 1",
        "employee_company_code": "VL"
      }
    ],
    "metadata": {
      "current_page": 1,
      "total_pages": 1,
      "total_items": 5,
      "items_per_page": 20
    }
  },
  "cause": {}
}